naust/__init__.py
naust/salts.py
naust/fram_strait/bottle.py
naust-0.1.2.dist-info/METADATA
naust-0.1.2.dist-info/WHEEL
naust-0.1.2.dist-info/licenses/LICENSE
naust-0.1.2.dist-info/RECORD
